rknn/__init__.py
rknn/api/__init__.py
rknn/api/act_equalization.cpython-310-x86_64-linux-gnu.so
rknn/api/base_utils.cpython-310-x86_64-linux-gnu.so
rknn/api/bias_correction.cpython-310-x86_64-linux-gnu.so
rknn/api/cpp_gen.cpython-310-x86_64-linux-gnu.so
rknn/api/custom_op.cpython-310-x86_64-linux-gnu.so
rknn/api/debug_rules.cpython-310-x86_64-linux-gnu.so
rknn/api/fuse_rules.cpython-310-x86_64-linux-gnu.so
rknn/api/graph_optimizer.cpython-310-x86_64-linux-gnu.so
rknn/api/hybrid_proposal.cpython-310-x86_64-linux-gnu.so
rknn/api/ir_graph.cpython-310-x86_64-linux-gnu.so
rknn/api/ir_utils.cpython-310-x86_64-linux-gnu.so
rknn/api/libcpputils2.cpython-310-x86_64-linux-gnu.so
rknn/api/load_checker.cpython-310-x86_64-linux-gnu.so
rknn/api/mmse_quant2.cpython-310-x86_64-linux-gnu.so
rknn/api/model_pruning.cpython-310-x86_64-linux-gnu.so
rknn/api/quant_optimizer.cpython-310-x86_64-linux-gnu.so
rknn/api/quant_utils.cpython-310-x86_64-linux-gnu.so
rknn/api/quantizer.cpython-310-x86_64-linux-gnu.so
rknn/api/rknn.py
rknn/api/rknn_base.cpython-310-x86_64-linux-gnu.so
rknn/api/rknn_convert.cpython-310-x86_64-linux-gnu.so
rknn/api/rknn_log.cpython-310-x86_64-linux-gnu.so
rknn/api/rknn_platform.cpython-310-x86_64-linux-gnu.so
rknn/api/rknn_runtime.cpython-310-x86_64-linux-gnu.so
rknn/api/rknn_utils.cpython-310-x86_64-linux-gnu.so
rknn/api/session.cpython-310-x86_64-linux-gnu.so
rknn/api/simulator.cpython-310-x86_64-linux-gnu.so
rknn/api/sparse_weight.cpython-310-x86_64-linux-gnu.so
rknn/api/weight_equalization.cpython-310-x86_64-linux-gnu.so
rknn_1.6-1.0.4.dist-info/METADATA
rknn_1.6-1.0.4.dist-info/WHEEL
rknn_1.6-1.0.4.dist-info/top_level.txt
rknn_1.6-1.0.4.dist-info/RECORD
