Metadata-Version: 2.1
Name: rknn-1.6
Version: 1.0.4
Summary: rknn_api
Author: ErnisMeshi
Author-email: ernis.meshi@student.uni-pr.edu
Classifier: Programming Language :: Python :: 3
Classifier: License :: OSI Approved :: MIT License
Classifier: Operating System :: OS Independent
